{
  "name": "CardVille",
  "version": "1.0.46",
  "mode": "ci-build-guard-mode-select-coherence-patch",
  "svg": "disabled",
  "pwa": "disabled",
  "notes": "Premium PNG asset batch applied with transparent cutout cleanup, WebP companions, expression cats, pack burst effects, math console, memory board, and active scene wiring.",
  "label": "Art bible + perfect-day mission route merge",
  "description": "Premium AAA art direction bible, prompt system, no-SVG policy, and asset generation rules."
}
